multiqc/__init__.py
multiqc/__main__.py
multiqc/multiqc.py
multiqc/modules/__init__.py
multiqc/modules/base_module.py
multiqc/modules/adapterRemoval/__init__.py
multiqc/modules/adapterRemoval/adapterRemoval.py
multiqc/modules/afterqc/__init__.py
multiqc/modules/afterqc/afterqc.py
multiqc/modules/bamtools/__init__.py
multiqc/modules/bamtools/bamtools.py
multiqc/modules/bamtools/stats.py
multiqc/modules/bbmap/__init__.py
multiqc/modules/bbmap/bbmap.py
multiqc/modules/bbmap/bbmap_filetypes.py
multiqc/modules/bbmap/plot_aqhist.py
multiqc/modules/bbmap/plot_basic_hist.py
multiqc/modules/bbmap/plot_bhist.py
multiqc/modules/bbmap/plot_bqhist.py
multiqc/modules/bbmap/plot_covhist.py
multiqc/modules/bbmap/plot_idhist.py
multiqc/modules/bbmap/plot_ihist.py
multiqc/modules/bbmap/plot_indelhist.py
multiqc/modules/bbmap/plot_mhist.py
multiqc/modules/bbmap/plot_qahist.py
multiqc/modules/bbmap/plot_qhist.py
multiqc/modules/bcftools/__init__.py
multiqc/modules/bcftools/bcftools.py
multiqc/modules/bcftools/stats.py
multiqc/modules/bcl2fastq/__init__.py
multiqc/modules/bcl2fastq/bcl2fastq.py
multiqc/modules/biobambam2/__init__.py
multiqc/modules/biobambam2/biobambam2.py
multiqc/modules/biobloomtools/__init__.py
multiqc/modules/biobloomtools/biobloomtools.py
multiqc/modules/biscuit/__init__.py
multiqc/modules/biscuit/biscuit.py
multiqc/modules/bismark/__init__.py
multiqc/modules/bismark/bismark.py
multiqc/modules/bowtie1/__init__.py
multiqc/modules/bowtie1/bowtie1.py
multiqc/modules/bowtie2/__init__.py
multiqc/modules/bowtie2/bowtie2.py
multiqc/modules/busco/__init__.py
multiqc/modules/busco/busco.py
multiqc/modules/bustools/__init__.py
multiqc/modules/bustools/bustools.py
multiqc/modules/clipandmerge/__init__.py
multiqc/modules/clipandmerge/clipandmerge.py
multiqc/modules/clusterflow/__init__.py
multiqc/modules/clusterflow/clusterflow.py
multiqc/modules/conpair/__init__.py
multiqc/modules/conpair/conpair.py
multiqc/modules/custom_content/__init__.py
multiqc_msk-1.11.dev0.dist-info/LICENSE
multiqc_msk-1.11.dev0.dist-info/METADATA
multiqc_msk-1.11.dev0.dist-info/WHEEL
multiqc_msk-1.11.dev0.dist-info/entry_points.txt
multiqc_msk-1.11.dev0.dist-info/top_level.txt
multiqc_msk-1.11.dev0.dist-info/RECORD
