Metadata-Version: 2.1
Name: multiqc-msk
Version: 1.11.dev0
Summary: Create aggregate bioinformatics analysis reports across many samples and tools
Home-page: http://multiqc.info
Author: Phil Ewels
Author-email: phil.ewels@scilifelab.se
License: GPLv3
Download-URL: https://github.com/ewels/MultiQC/tarball/master
Keywords: bioinformatics,biology,sequencing,NGS,next generation sequencing,quality control
Platform: UNKNOWN
Classifier: Development Status :: 5 - Production/Stable
Classifier: Environment :: Console
Classifier: Environment :: Web Environment
Classifier: Intended Audience :: Science/Research
Classifier: License :: OSI Approved :: GNU General Public License v3 (GPLv3)
Classifier: Natural Language :: English
Classifier: Operating System :: MacOS :: MacOS X
Classifier: Operating System :: POSIX
Classifier: Operating System :: Unix
Classifier: Programming Language :: Python
Classifier: Programming Language :: JavaScript
Classifier: Topic :: Scientific/Engineering
Classifier: Topic :: Scientific/Engineering :: Bio-Informatics
Classifier: Topic :: Scientific/Engineering :: Visualization
Requires-Dist: matplotlib (>=2.1.1)
Requires-Dist: networkx (>=2.5.1)
Requires-Dist: numpy
Requires-Dist: click
Requires-Dist: coloredlogs
Requires-Dist: future (>0.14.0)
Requires-Dist: jinja2 (>=2.9)
Requires-Dist: lzstring
Requires-Dist: markdown
Requires-Dist: pyyaml (>=4)
Requires-Dist: requests
Requires-Dist: rich (>=10)
Requires-Dist: simplejson
Requires-Dist: spectra (>=0.0.10)
